[{"english":"be","turkish":"olmak","level":"A1"},{"english":"have","turkish":"sahip olmak","level":"A1"},{"english":"do","turkish":"yapmak","level":"A1"},{"english":"say","turkish":"söylemek","level":"A1"},{"english":"go","turkish":"gitmek","level":"A1"},{"english":"get","turkish":"almak","level":"A1"},{"english":"make","turkish":"yapmak","level":"A1"},{"english":"know","turkish":"bilmek","level":"A1"},{"english":"think","turkish":"düşünmek","level":"A1"},{"english":"take","turkish":"almak","level":"A1"},{"english":"see","turkish":"görmek","level":"A1"},{"english":"come","turkish":"gelmek","level":"A1"},{"english":"want","turkish":"istemek","level":"A1"},{"english":"use","turkish":"kullanmak","level":"A1"},{"english":"find","turkish":"bulmak","level":"A1"},{"english":"give","turkish":"vermek","level":"A1"},{"english":"tell","turkish":"söylemek","level":"A1"},{"english":"work","turkish":"çalışmak","level":"A1"},{"english":"call","turkish":"aramak","level":"A1"},{"english":"try","turkish":"denemek","level":"A1"},{"english":"ask","turkish":"sormak","level":"A1"},{"english":"need","turkish":"ihtiyaç duymak","level":"A1"},{"english":"feel","turkish":"hissetmek","level":"A1"},{"english":"play","turkish":"çalmak","level":"A1"},{"english":"run","turkish":"koşmak","level":"A1"},{"english":"like","turkish":"sevmek","level":"A1"},{"english":"live","turkish":"yaşamak","level":"A1"},{"english":"write","turkish":"yazmak","level":"A1"},{"english":"sit","turkish":"oturmak","level":"A1"},{"english":"read","turkish":"okumak","level":"A1"},{"english":"open","turkish":"açmak","level":"A1"},{"english":"walk","turkish":"yürümek","level":"A1"},{"english":"love","turkish":"sevmek","level":"A1"},{"english":"become","turkish":"olmak","level":"A2"},{"english":"leave","turkish":"ayrılmak","level":"A2"},{"english":"put","turkish":"koymak","level":"A2"},{"english":"mean","turkish":"anlamına gelmek","level":"A2"},{"english":"keep","turkish":"tutmak","level":"A2"},{"english":"let","turkish":"izin vermek","level":"A2"},{"english":"begin","turkish":"başlamak","level":"A2"},{"english":"seem","turkish":"görünmek","level":"A2"},{"english":"help","turkish":"yardım etmek","level":"A2"},{"english":"talk","turkish":"konuşmak","level":"A2"},{"english":"turn","turkish":"dönmek","level":"A2"},{"english":"start","turkish":"başlamak","level":"A2"},{"english":"show","turkish":"göstermek","level":"A2"},{"english":"hear","turkish":"duymak","level":"A2"},{"english":"move","turkish":"hareket etmek","level":"A2"},{"english":"believe","turkish":"inanmak","level":"A2"},{"english":"hold","turkish":"tutmak","level":"A2"},{"english":"bring","turkish":"getirmek","level":"A2"},{"english":"happen","turkish":"olmak","level":"A2"},{"english":"stand","turkish":"ayakta durmak","level":"A2"},{"english":"lose","turkish":"kaybetmek","level":"A2"},{"english":"pay","turkish":"ödemek","level":"A2"},{"english":"meet","turkish":"buluşmak","level":"A2"},{"english":"continue","turkish":"devam etmek","level":"A2"},{"english":"learn","turkish":"öğrenmek","level":"A2"},{"english":"change","turkish":"değişmek","level":"A2"},{"english":"understand","turkish":"anlamak","level":"A2"},{"english":"watch","turkish":"izlemek","level":"A2"},{"english":"follow","turkish":"takip etmek","level":"A2"},{"english":"stop","turkish":"durdurmak","level":"A2"},{"english":"speak","turkish":"konuşmak","level":"A2"},{"english":"add","turkish":"eklemek","level":"A2"},{"english":"spend","turkish":"harcamak","level":"A2"},{"english":"grow","turkish":"büyümek","level":"A2"},{"english":"win","turkish":"kazanmak","level":"A2"},{"english":"remember","turkish":"hatırlamak","level":"A2"},{"english":"buy","turkish":"satın almak","level":"A2"},{"english":"wait","turkish":"beklemek","level":"A2"},{"english":"die","turkish":"ölmek","level":"A2"},{"english":"send","turkish":"göndermek","level":"A2"},{"english":"build","turkish":"inşa etmek","level":"A2"},{"english":"stay","turkish":"kalmak","level":"A2"},{"english":"fall","turkish":"düşmek","level":"A2"},{"english":"cut","turkish":"kesmek","level":"A2"},{"english":"join","turkish":"katılmak","level":"A2"},{"english":"return","turkish":"dönmek","level":"A2"},{"english":"laugh","turkish":"gülmek","level":"A2"},{"english":"listen","turkish":"dinlemek","level":"A2"},{"english":"hope","turkish":"ummak","level":"A2"},{"english":"carry","turkish":"taşımak","level":"A2"},{"english":"visit","turkish":"ziyaret etmek","level":"A2"},{"english":"dance","turkish":"dans etmek","level":"A2"},{"english":"arrive","turkish":"varmak","level":"A2"},{"english":"prepare","turkish":"hazırlamak","level":"A2"},{"english":"search","turkish":"aramak","level":"A2"},{"english":"choose","turkish":"seçmek","level":"A2"},{"english":"decide","turkish":"karar vermek","level":"A2"},{"english":"forget","turkish":"unutmak","level":"A2"},{"english":"finish","turkish":"bitirmek","level":"A2"},{"english":"pass","turkish":"geçmek","level":"A2"},{"english":"cook","turkish":"pişirmek","level":"A2"},{"english":"clean","turkish":"temizlemek","level":"A2"},{"english":"sell","turkish":"satmak","level":"A2"},{"english":"receive","turkish":"almak","level":"A2"},{"english":"check","turkish":"kontrol etmek","level":"A2"},{"english":"study","turkish":"çalışmak","level":"A2"},{"english":"copy","turkish":"kopyalamak","level":"A2"},{"english":"book","turkish":"rezervasyon yapmak","level":"B1"},{"english":"provide","turkish":"sağlamak","level":"B1"},{"english":"include","turkish":"dahil etmek","level":"B1"},{"english":"set","turkish":"ayarlamak","level":"B1"},{"english":"lead","turkish":"liderlik yapmak","level":"B1"},{"english":"create","turkish":"yaratmak","level":"B1"},{"english":"allow","turkish":"izin vermek","level":"B1"},{"english":"offer","turkish":"sunmak","level":"B1"},{"english":"consider","turkish":"düşünmek","level":"B1"},{"english":"appear","turkish":"görünmek","level":"B1"},{"english":"serve","turkish":"servis yapmak","level":"B1"},{"english":"expect","turkish":"beklemek","level":"B1"},{"english":"reach","turkish":"ulaşmak","level":"B1"},{"english":"kill","turkish":"öldürmek","level":"B1"},{"english":"remain","turkish":"kalmak","level":"B1"},{"english":"draw","turkish":"çizmek","level":"B1"},{"english":"teach","turkish":"öğretmek","level":"B1"},{"english":"explain","turkish":"açıklamak","level":"B1"},{"english":"fight","turkish":"savaşmak","level":"B1"},{"english":"save","turkish":"kaydetmek","level":"B1"},{"english":"accept","turkish":"kabul etmek","level":"B1"},{"english":"recognize","turkish":"tanımak","level":"B1"},{"english":"mention","turkish":"bahsetmek","level":"B1"},{"english":"invite","turkish":"davet etmek","level":"B1"},{"english":"introduce","turkish":"tanıtmak","level":"B1"},{"english":"improve","turkish":"iyileştirmek","level":"B1"},{"english":"manage","turkish":"yönetmek","level":"B1"},{"english":"require","turkish":"gerektirmek","level":"B1"},{"english":"treat","turkish":"tedavi etmek","level":"B1"},{"english":"prevent","turkish":"önlemek","level":"B1"},{"english":"refuse","turkish":"reddetmek","level":"B1"},{"english":"protect","turkish":"korumak","level":"B1"},{"english":"agree","turkish":"katılmak","level":"B1"},{"english":"earn","turkish":"kazanmak","level":"B1"},{"english":"hire","turkish":"işe almak","level":"B1"},{"english":"fire","turkish":"işten çıkarmak","level":"B1"},{"english":"train","turkish":"eğitmek","level":"B1"},{"english":"repair","turkish":"tamir etmek","level":"B1"},{"english":"paint","turkish":"boyamak","level":"B1"},{"english":"design","turkish":"tasarlamak","level":"B1"},{"english":"develop","turkish":"geliştirmek","level":"B1"},{"english":"produce","turkish":"üretmek","level":"B1"},{"english":"order","turkish":"sipariş vermek","level":"B1"},{"english":"cancel","turkish":"iptal etmek","level":"B1"},{"english":"deliver","turkish":"teslim etmek","level":"B1"},{"english":"pack","turkish":"paketlemek","level":"B1"},{"english":"collect","turkish":"toplamak","level":"B1"},{"english":"share","turkish":"paylaşmak","level":"B1"},{"english":"compare","turkish":"karşılaştırmak","level":"B1"},{"english":"organize","turkish":"düzenlemek","level":"B1"},{"english":"plan","turkish":"planlamak","level":"B1"},{"english":"sign","turkish":"imzalamak","level":"B1"},{"english":"support","turkish":"desteklemek","level":"B1"},{"english":"advise","turkish":"tavsiye etmek","level":"B1"},{"english":"suggest","turkish":"önermek","level":"B1"},{"english":"discuss","turkish":"tartışmak","level":"B1"},{"english":"argue","turkish":"tartışmak","level":"B1"},{"english":"complain","turkish":"şikayet etmek","level":"B1"},{"english":"apologize","turkish":"özür dilemek","level":"B1"},{"english":"congratulate","turkish":"tebrik etmek","level":"B1"},{"english":"celebrate","turkish":"kutlamak","level":"B1"},{"english":"attend","turkish":"katılmak","level":"B1"},{"english":"apply","turkish":"başvurmak","level":"B1"},{"english":"interview","turkish":"görüşme yapmak","level":"B1"},{"english":"retire","turkish":"emekli olmak","level":"B1"},{"english":"resign","turkish":"istifa etmek","level":"B1"},{"english":"graduate","turkish":"mezun olmak","level":"B1"},{"english":"research","turkish":"araştırma yapmak","level":"B1"},{"english":"discover","turkish":"keşfetmek","level":"B1"},{"english":"invent","turkish":"icat etmek","level":"B1"},{"english":"print","turkish":"basmak","level":"B1"},{"english":"delete","turkish":"silmek","level":"B1"},{"english":"download","turkish":"indirmek","level":"B1"},{"english":"upload","turkish":"yüklemek","level":"B1"},{"english":"click","turkish":"tıklamak","level":"B1"},{"english":"charge","turkish":"şarj etmek","level":"B1"},{"english":"switch","turkish":"açmak/kapatmak","level":"B1"},{"english":"connect","turkish":"bağlanmak","level":"B1"},{"english":"disconnect","turkish":"bağlantıyı kesmek","level":"B1"},{"english":"restart","turkish":"yeniden başlatmak","level":"B1"},{"english":"install","turkish":"kurmak","level":"B1"},{"english":"update","turkish":"güncellemek","level":"B1"},{"english":"record","turkish":"kaydetmek","level":"B1"},{"english":"pause","turkish":"duraklatmak","level":"B1"},{"english":"fast-forward","turkish":"ileri sarmak","level":"B1"},{"english":"rewind","turkish":"geri sarmak","level":"B1"},{"english":"zoom","turkish":"yakınlaştırmak","level":"B1"},{"english":"focus","turkish":"odaklanmak","level":"B1"},{"english":"adjust","turkish":"ayarlamak","level":"B1"},{"english":"measure","turkish":"ölçmek","level":"B1"},{"english":"calculate","turkish":"hesaplamak","level":"B1"},{"english":"estimate","turkish":"tahmin etmek","level":"B1"},{"english":"solve","turkish":"çözmek","level":"B1"},{"english":"restructure","turkish":"yeniden yapılandırmak","level":"B2"},{"english":"mediate","turkish":"arabuluculuk yapmak","level":"B2"},{"english":"rehabilitate","turkish":"rehabilitasyon yapmak","level":"B2"},{"english":"counsel","turkish":"danışmanlık yapmak","level":"B2"},{"english":"promote","turkish":"terfi ettirmek","level":"B2"},{"english":"publish","turkish":"yayınlamak","level":"B2"},{"english":"edit","turkish":"düzenlemek","level":"B2"},{"english":"translate","turkish":"çevirmek","level":"B2"},{"english":"analyze","turkish":"analiz etmek","level":"B2"},{"english":"experiment","turkish":"deney yapmak","level":"B2"},{"english":"observe","turkish":"gözlemlemek","level":"B2"},{"english":"predict","turkish":"tahmin etmek","level":"B2"},{"english":"confirm","turkish":"doğrulamak","level":"B2"},{"english":"investigate","turkish":"araştırmak","level":"B2"},{"english":"inspect","turkish":"incelemek","level":"B2"},{"english":"evaluate","turkish":"değerlendirmek","level":"B2"},{"english":"recommend","turkish":"tavsiye etmek","level":"B2"},{"english":"guarantee","turkish":"garanti etmek","level":"B2"},{"english":"insure","turkish":"sigortalamak","level":"B2"},{"english":"claim","turkish":"talep etmek","level":"B2"},{"english":"negotiate","turkish":"pazarlık yapmak","level":"B2"},{"english":"contract","turkish":"sözleşme yapmak","level":"B2"},{"english":"sponsor","turkish":"sponsor olmak","level":"B2"},{"english":"donate","turkish":"bağışlamak","level":"B2"},{"english":"invest","turkish":"yatırım yapmak","level":"B2"},{"english":"profit","turkish":"kâr elde etmek","level":"B2"},{"english":"budget","turkish":"bütçeleştirmek","level":"B2"},{"english":"fund","turkish":"finanse etmek","level":"B2"},{"english":"audit","turkish":"denetlemek","level":"B2"},{"english":"bill","turkish":"fatura kesmek","level":"B2"},{"english":"deposit","turkish":"yatırmak","level":"B2"},{"english":"withdraw","turkish":"çekmek","level":"B2"},{"english":"transfer","turkish":"transfer etmek","level":"B2"},{"english":"exchange","turkish":"değiştirmek","level":"B2"},{"english":"import","turkish":"ithal etmek","level":"B2"},{"english":"export","turkish":"ihraç etmek","level":"B2"},{"english":"manufacture","turkish":"üretmek","level":"B2"},{"english":"assemble","turkish":"monte etmek","level":"B2"},{"english":"distribute","turkish":"dağıtmak","level":"B2"},{"english":"market","turkish":"pazarlamak","level":"B2"},{"english":"advertise","turkish":"reklam yapmak","level":"B2"},{"english":"brand","turkish":"markalaştırmak","level":"B2"},{"english":"launch","turkish":"piyasaya sürmek","level":"B2"},{"english":"compete","turkish":"rekabet etmek","level":"B2"},{"english":"merge","turkish":"birleşmek","level":"B2"},{"english":"acquire","turkish":"satın almak","level":"B2"},{"english":"expand","turkish":"genişletmek","level":"B2"},{"english":"dismiss","turkish":"kovmak","level":"B2"},{"english":"recruit","turkish":"işe almak","level":"B2"},{"english":"motivate","turkish":"motive etmek","level":"B2"},{"english":"discipline","turkish":"disipline etmek","level":"B2"},{"english":"reward","turkish":"ödüllendirmek","level":"B2"},{"english":"penalize","turkish":"cezalandırmak","level":"B2"},{"english":"authorize","turkish":"onaylamak","level":"B2"},{"english":"prohibit","turkish":"yasaklamak","level":"B2"},{"english":"regulate","turkish":"düzenlemek","level":"B2"},{"english":"legislate","turkish":"yasalaştırmak","level":"B2"},{"english":"govern","turkish":"yönetmek","level":"B2"},{"english":"elect","turkish":"seçmek","level":"B2"},{"english":"campaign","turkish":"kampanya yapmak","level":"B2"},{"english":"vote","turkish":"oy vermek","level":"B2"},{"english":"debate","turkish":"tartışmak","level":"B2"},{"english":"protest","turkish":"protesto etmek","level":"B2"},{"english":"demonstrate","turkish":"gösteri yapmak","level":"B2"},{"english":"rally","turkish":"miting düzenlemek","level":"B2"},{"english":"lobby","turkish":"lobi yapmak","level":"B2"},{"english":"arbitrate","turkish":"hakemlik yapmak","level":"C2"},{"english":"reconcile","turkish":"barıştırmak","level":"B2"},{"english":"integrate","turkish":"entegre etmek","level":"B2"},{"english":"segregate","turkish":"ayırmak","level":"B2"},{"english":"collaborate","turkish":"işbirliği yapmak","level":"C1"},{"english":"cooperate","turkish":"işbirliği yapmak","level":"B2"},{"english":"coordinate","turkish":"koordine etmek","level":"B2"},{"english":"communicate","turkish":"iletişim kurmak","level":"B2"},{"english":"persuade","turkish":"ikna etmek","level":"B2"},{"english":"convince","turkish":"inandırmak","level":"B2"},{"english":"inspire","turkish":"ilham vermek","level":"B2"},{"english":"encourage","turkish":"cesaretlendirmek","level":"B2"},{"english":"discourage","turkish":"caydırmak","level":"B2"},{"english":"appreciate","turkish":"takdir etmek","level":"B2"},{"english":"criticize","turkish":"eleştirmek","level":"B2"},{"english":"praise","turkish":"övmek","level":"B2"},{"english":"blame","turkish":"suçlamak","level":"B2"},{"english":"forgive","turkish":"affetmek","level":"B2"},{"english":"punish","turkish":"cezalandırmak","level":"B2"},{"english":"diagnose","turkish":"teşhis koymak","level":"B2"},{"english":"prescribe","turkish":"reçete yazmak","level":"B2"},{"english":"operate","turkish":"ameliyat yapmak","level":"B2"},{"english":"vaccinate","turkish":"aşılamak","level":"B2"},{"english":"quarantine","turkish":"karantinaya almak","level":"B2"},{"english":"therapize","turkish":"terapi yapmak","level":"B2"},{"english":"hypnotize","turkish":"hipnotize etmek","level":"B2"},{"english":"exercise","turkish":"egzersiz yapmak","level":"B2"},{"english":"meditate","turkish":"meditasyon yapmak","level":"B2"},{"english":"relax","turkish":"rahatlamak","level":"B2"},{"english":"energize","turkish":"enerji vermek","level":"B2"},{"english":"refresh","turkish":"ferahlatmak","level":"B2"},{"english":"stimulate","turkish":"uyarmak","level":"B2"},{"english":"sedate","turkish":"sakinleştirmek","level":"B2"},{"english":"intoxicate","turkish":"sarhoş etmek","level":"B2"},{"english":"sober","turkish":"ayılmak","level":"B2"},{"english":"recover","turkish":"iyileşmek","level":"B2"},{"english":"survive","turkish":"hayatta kalmak","level":"B2"},{"english":"advocate","turkish":"savunmak","level":"C1"},{"english":"allocate","turkish":"tahsis etmek","level":"C1"},{"english":"amend","turkish":"değiştirmek","level":"C1"},{"english":"anticipate","turkish":"önceden tahmin etmek","level":"C1"},{"english":"ascertain","turkish":"tespit etmek","level":"C1"},{"english":"attribute","turkish":"atfetmek","level":"C1"},{"english":"commence","turkish":"başlamak","level":"C1"},{"english":"comply","turkish":"uymak","level":"C1"},{"english":"confer","turkish":"görüşmek","level":"C1"},{"english":"consolidate","turkish":"birleştirmek","level":"C1"},{"english":"consult","turkish":"danışmak","level":"C1"},{"english":"contend","turkish":"iddia etmek","level":"C1"},{"english":"contradict","turkish":"çelişkili olmak","level":"C1"},{"english":"convene","turkish":"toplamak","level":"C1"},{"english":"convey","turkish":"iletmek","level":"C1"},{"english":"deduce","turkish":"çıkarmak","level":"C1"},{"english":"deem","turkish":"saymak","level":"C1"},{"english":"defer","turkish":"ertelemek","level":"C1"},{"english":"deliberate","turkish":"kasten yapmak","level":"C1"},{"english":"denote","turkish":"ifade etmek","level":"C1"},{"english":"deprive","turkish":"mahrum bırakmak","level":"C1"},{"english":"derive","turkish":"elde etmek","level":"C1"},{"english":"devise","turkish":"tasarlamak","level":"C1"},{"english":"discern","turkish":"ayırt etmek","level":"C1"},{"english":"disclose","turkish":"ifşa etmek","level":"C1"},{"english":"disprove","turkish":"çürütmek","level":"C1"},{"english":"disrupt","turkish":"bozmak","level":"C1"},{"english":"dissolve","turkish":"çözmek","level":"C1"},{"english":"distinguish","turkish":"ayırt etmek","level":"C1"},{"english":"diverge","turkish":"ayrılmak","level":"C1"},{"english":"diversify","turkish":"çeşitlendirmek","level":"C1"},{"english":"divert","turkish":"saptırmak","level":"C1"},{"english":"divest","turkish":"elden çıkarmak","level":"C1"},{"english":"elaborate","turkish":"ayrıntılandırmak","level":"C1"},{"english":"elicit","turkish":"ortaya çıkarmak","level":"C1"},{"english":"elude","turkish":"kaçmak","level":"C1"},{"english":"embody","turkish":"temsil etmek","level":"C1"},{"english":"empower","turkish":"yetki vermek","level":"C1"},{"english":"enact","turkish":"yürürlüğe koymak","level":"C1"},{"english":"encompass","turkish":"kapsamak","level":"C1"},{"english":"endure","turkish":"dayanmak","level":"C1"},{"english":"enforce","turkish":"uygulamak","level":"C1"},{"english":"enhance","turkish":"geliştirmek","level":"C1"},{"english":"enumerate","turkish":"saymak","level":"C1"},{"english":"equate","turkish":"eşitlemek","level":"C1"},{"english":"eradicate","turkish":"yok etmek","level":"C1"},{"english":"escalate","turkish":"tırmandırmak","level":"C1"},{"english":"evade","turkish":"kaçınmak","level":"C1"},{"english":"exacerbate","turkish":"kötüleştirmek","level":"C1"},{"english":"abrogate","turkish":"feshetmek","level":"C2"},{"english":"acquiesce","turkish":"razı olmak","level":"C2"},{"english":"admonish","turkish":"ihtar etmek","level":"C2"},{"english":"ameliorate","turkish":"iyileştirmek","level":"C2"},{"english":"annihilate","turkish":"yok etmek","level":"C2"},{"english":"anoint","turkish":"meshetmek","level":"C2"},{"english":"appease","turkish":"yatıştırmak","level":"C2"},{"english":"attenuate","turkish":"zayıflatmak","level":"C2"},{"english":"avow","turkish":"itiraf etmek","level":"C2"},{"english":"belie","turkish":"yanlış göstermek","level":"C2"},{"english":"bemoan","turkish":"yakınmak","level":"C2"},{"english":"berate","turkish":"azarlama","level":"C2"},{"english":"bewilder","turkish":"şaşırtmak","level":"C2"},{"english":"blaspheme","turkish":"küfretmek","level":"C2"},{"english":"bolster","turkish":"desteklemek","level":"C2"},{"english":"browbeat","turkish":"sindirmek","level":"C2"},{"english":"calumniate","turkish":"iftira etmek","level":"C2"},{"english":"canonize","turkish":"aziz saymak","level":"C2"},{"english":"capitulate","turkish":"teslim olmak","level":"C2"},{"english":"castigate","turkish":"kınamak","level":"C2"},{"english":"cavil","turkish":"kusur bulmak","level":"C2"},{"english":"censure","turkish":"kınamak","level":"C2"},{"english":"chide","turkish":"paylamak","level":"C2"},{"english":"circumlocute","turkish":"dolaylı konuşmak","level":"C2"},{"english":"circumscribe","turkish":"sınırlamak","level":"C2"},{"english":"circumvent","turkish":"etrafından dolaşmak","level":"C2"},{"english":"commiserate","turkish":"acımak","level":"C2"},{"english":"condone","turkish":"hoş görmek","level":"C2"},{"english":"confabulate","turkish":"uydurmak","level":"C2"},{"english":"connive","turkish":"göz yummak","level":"C2"},{"english":"consecrate","turkish":"kutsamak","level":"C2"},{"english":"contravene","turkish":"ihlal etmek","level":"C2"},{"english":"corroborate","turkish":"doğrulamak","level":"C2"},{"english":"countermand","turkish":"geri almak","level":"C2"},{"english":"decimate","turkish":"telef etmek","level":"C2"},{"english":"declaim","turkish":"nutuk çekmek","level":"C2"},{"english":"defame","turkish":"iftira etmek","level":"C2"},{"english":"degenerate","turkish":"yozlaşmak","level":"C2"},{"english":"deify","turkish":"tanrılaştırmak","level":"C2"},{"english":"delimit","turkish":"sınırlandırmak","level":"C2"},{"english":"delineate","turkish":"betimlemek","level":"C2"},{"english":"denigrate","turkish":"karalamak","level":"C2"},{"english":"deprecate","turkish":"kınamak","level":"C2"},{"english":"deride","turkish":"alay etmek","level":"C2"},{"english":"desecrate","turkish":"saygısızca davranmak","level":"C2"},{"english":"despoil","turkish":"yağmalamak","level":"C2"},{"english":"detest","turkish":"nefret etmek","level":"C2"},{"english":"detract","turkish":"eksiltmek","level":"C2"},{"english":"devastate","turkish":"yıkmak","level":"C2"}]