[{"english":"break down","turkish":"bozulmak/arızalanmak","level":"B1"},{"english":"break up","turkish":"ayrılmak/sona ermek","level":"B1"},{"english":"bring up","turkish":"bahsetmek/yetiştirmek","level":"B1"},{"english":"call back","turkish":"geri aramak","level":"B1"},{"english":"call off","turkish":"iptal etmek","level":"B1"},{"english":"carry on","turkish":"devam etmek","level":"A2"},{"english":"carry out","turkish":"gerçekleştirmek","level":"B1"},{"english":"catch up","turkish":"yetişmek/haberi olmak","level":"B1"},{"english":"check in","turkish":"otele giriş yapmak","level":"B1"},{"english":"check out","turkish":"hesabı ödemek/odadan çıkmak","level":"B1"},{"english":"cheer up","turkish":"neşelenmek","level":"B1"},{"english":"come across","turkish":"tesadüfen bulmak","level":"B1"},{"english":"come back","turkish":"geri dönmek","level":"A2"},{"english":"come over","turkish":"uğramak/ziyaret etmek","level":"B1"},{"english":"come up","turkish":"ortaya çıkmak","level":"B1"},{"english":"count on","turkish":"güvenmek/yakın olmak","level":"B1"},{"english":"cut down","turkish":"azaltmak","level":"B1"},{"english":"cut off","turkish":"kesmek/kapatmak","level":"B1"},{"english":"do over","turkish":"tekrar yapmak","level":"B2"},{"english":"drop in","turkish":"uğramak","level":"B1"},{"english":"drop off","turkish":"bırakmak/indirmek","level":"B1"},{"english":"drop out","turkish":"bırakmak (okulu)","level":"B2"},{"english":"eat out","turkish":"dışarıda yemek yemek","level":"B1"},{"english":"fall apart","turkish":"dağılmak/parçalanmak","level":"B1"},{"english":"fall behind","turkish":"geride kalmak","level":"B1"},{"english":"fall out","turkish":"kavga etmek","level":"B1"},{"english":"feel up to","turkish":"hazır hissetmek","level":"B2"},{"english":"figure out","turkish":"çözmek/anlamak","level":"B1"},{"english":"fill in","turkish":"doldurmak/yedeklemek","level":"B1"},{"english":"fill out","turkish":"doldurmak (form)","level":"B1"},{"english":"find out","turkish":"öğrenmek/keşfetmek","level":"A2"},{"english":"get along","turkish":"anlaşmak","level":"A2"},{"english":"get away","turkish":"kaçmak/tatil yapmak","level":"B1"},{"english":"get back","turkish":"geri dönmek","level":"A2"},{"english":"get by","turkish":"idare etmek","level":"B1"},{"english":"get in","turkish":"binmek/gelmek","level":"B1"},{"english":"get off","turkish":"inmek/cezadan kurtulmak","level":"B1"},{"english":"get on","turkish":"binmek/anlaşmak","level":"A2"},{"english":"get out","turkish":"çıkmak","level":"A1"},{"english":"get over","turkish":"atlatmak/üstesinden gelmek","level":"B1"},{"english":"get through","turkish":"bitirmek/ulaşmak","level":"B1"},{"english":"get up","turkish":"kalkmak (yataktan)","level":"A1"},{"english":"give away","turkish":"vermek/bedava dağıtmak","level":"B1"},{"english":"give in","turkish":"pes etmek","level":"B1"},{"english":"give out","turkish":"dağıtmak/bozulmak","level":"B1"},{"english":"give up","turkish":"vazgeçmek","level":"A2"},{"english":"go ahead","turkish":"devam et","level":"B1"},{"english":"go back","turkish":"geri gitmek","level":"A2"},{"english":"go on","turkish":"devam etmek/olmak","level":"A2"},{"english":"go out","turkish":"dışarı çıkmak","level":"A2"},{"english":"go over","turkish":"incelemek","level":"B1"},{"english":"grow up","turkish":"büyümek","level":"A2"},{"english":"hang on","turkish":"beklemek/dayanmak","level":"B1"},{"english":"hang up","turkish":"kapatmak (telefon)","level":"B1"},{"english":"hold back","turkish":"engellemek/çekingen olmak","level":"B1"},{"english":"hold on","turkish":"beklemek","level":"A2"},{"english":"hold up","turkish":"soygun yapmak/ertemek","level":"B1"},{"english":"hurry up","turkish":"acele etmek","level":"A2"},{"english":"keep on","turkish":"devam etmek","level":"A2"},{"english":"keep up","turkish":"yetişmek/ sürdürmek","level":"B1"},{"english":"knock out","turkish":"bayıltmak/üretmek","level":"B1"},{"english":"let down","turkish":"hayal kırıklığına uğratmak","level":"B1"},{"english":"let in","turkish":"içeri almak","level":"B1"},{"english":"let out","turkish":"dışarı çıkarmak","level":"B1"},{"english":"lie down","turkish":"uzanmak","level":"A2"},{"english":"look after","turkish":"bakmak/ilgilenmek","level":"A2"},{"english":"look back","turkish":"geriye bakmak","level":"B1"},{"english":"look forward to","turkish":"sabırsızlıkla beklemek","level":"B1"},{"english":"look into","turkish":"araştırmak","level":"B1"},{"english":"look out","turkish":"dikkat etmek","level":"B1"},{"english":"look up","turkish":"bakmak (sözlükte)","level":"B1"},{"english":"make up","turkish":"makyaj yapmak/barışmak","level":"B1"},{"english":"mix up","turkish":"karıştırmak","level":"B1"},{"english":"move in","turkish":"taşınmak (eve)","level":"B1"},{"english":"move out","turkish":"taşınmak (evden)","level":"B1"},{"english":"pass away","turkish":"vefat etmek","level":"B1"},{"english":"pass out","turkish":"bayılmak/dağıtmak","level":"B1"},{"english":"pay back","turkish":"geri ödemek","level":"B1"},{"english":"pick up","turkish":"almak/öğrenmek","level":"A2"},{"english":"point out","turkish":"işaret etmek","level":"B1"},{"english":"pull over","turkish":"kenara çekmek","level":"B1"},{"english":"put away","turkish":"kaldırmak","level":"B1"},{"english":"put down","turkish":"indirmek/not almak","level":"B1"},{"english":"put off","turkish":"ertelemek","level":"B1"},{"english":"put on","turkish":"giymek/yakmak","level":"A1"},{"english":"put out","turkish":"söndürmek/rahatsız etmek","level":"B1"},{"english":"put up","turkish":"asmak/kaldırmak","level":"B1"},{"english":"run into","turkish":"karşılaşmak","level":"B1"},{"english":"run out","turkish":"bitmek","level":"A2"},{"english":"run over","turkish":"ezmek/tekrar etmek","level":"B1"},{"english":"set up","turkish":"kurmak/organize etmek","level":"B1"},{"english":"show off","turkish":"övünmek","level":"B1"},{"english":"show up","turkish":"gelmek/görünmek","level":"B1"},{"english":"shut up","turkish":"susmak","level":"B1"},{"english":"sit down","turkish":"oturmak","level":"A1"},{"english":"speak up","turkish":"daha yüksek sesle konuşmak","level":"B1"},{"english":"stand up","turkish":"ayağa kalkmak","level":"A1"},{"english":"take after","turkish":"benzemek","level":"B1"},{"english":"take apart","turkish":"sökmek","level":"B2"},{"english":"take back","turkish":"geri almak/özür dilemek","level":"B1"},{"english":"take down","turkish":"indirmek/not almak","level":"B1"},{"english":"take in","turkish":"anlamak/giyim daraltmak","level":"B1"},{"english":"take off","turkish":"kalkmak/çıkarmak","level":"A2"},{"english":"take on","turkish":"üstlenmek/işe almak","level":"B1"},{"english":"take out","turkish":"çıkarmak/ödeme yapmak","level":"B1"},{"english":"take over","turkish":"devralmak","level":"B1"},{"english":"take up","turkish":"kaplamak/ilgi duymak","level":"B1"},{"english":"talk back","turkish":"ters cevap vermek","level":"B2"},{"english":"talk over","turkish":"tartışmak","level":"B2"},{"english":"tell apart","turkish":"ayırt etmek","level":"B2"},{"english":"tell off","turkish":"azarlamak","level":"B2"},{"english":"think over","turkish":"düşünmek","level":"B1"},{"english":"throw away","turkish":"atmak","level":"A2"},{"english":"throw out","turkish":"atmak/ kovmak","level":"B1"},{"english":"tidy up","turkish":"düzenlemek","level":"B1"},{"english":"try on","turkish":"giymek denemek","level":"B1"},{"english":"try out","turkish":"denemek","level":"B1"},{"english":"turn down","turkish":"reddetmek/söndürmek","level":"B1"},{"english":"turn into","turkish":"dönüşmek","level":"B1"},{"english":"turn on","turkish":"açmak","level":"A2"},{"english":"turn up","turkish":"çıkmak/bulunmak","level":"B1"},{"english":"use up","turkish":"tüketmek","level":"B1"},{"english":"wait on","turkish":"servis yapmak","level":"B1"},{"english":"wake up","turkish":"uyanmak","level":"A1"},{"english":"walk out","turkish":"terk etmek","level":"B2"},{"english":"warm up","turkish":"ısınmak","level":"B1"},{"english":"watch out","turkish":"dikkat etmek","level":"B1"},{"english":"wear out","turkish":"yıpratmak","level":"B1"},{"english":"work out","turkish":"çözmek/egzersiz yapmak","level":"B1"},{"english":"write down","turkish":"not almak","level":"A2"},{"english":"ask after","turkish":"halini sormak","level":"B2"},{"english":"ask around","turkish":"etrafa sormak","level":"B1"},{"english":"back away","turkish":"geri çekilmek","level":"B2"},{"english":"back off","turkish":"vazgeçmek","level":"B2"},{"english":"back up","turkish":"yedeklemek/desteklemek","level":"B1"},{"english":"blow up","turkish":"patlamak/öfkelenmek","level":"B1"},{"english":"branch out","turkish":"yeni alana girmek","level":"B2"},{"english":"brush up","turkish":"tazelemek","level":"B2"},{"english":"burn down","turkish":"yanmak (bina)","level":"B2"},{"english":"burn out","turkish":"tükenmek","level":"B2"},{"english":"calm down","turkish":"sakinleşmek","level":"A2"},{"english":"cash in","turkish":"kâr etmek","level":"B2"},{"english":"catch on","turkish":"anlamak/popüler olmak","level":"B1"},{"english":"chase away","turkish":"kovmak","level":"B2"},{"english":"chew over","turkish":"iyice düşünmek","level":"B2"},{"english":"chip in","turkish":"katkıda bulunmak","level":"B2"},{"english":"clam up","turkish":"susmak","level":"B2"},{"english":"clear out","turkish":"temizlemek/çekilmek","level":"B2"},{"english":"clear up","turkish":"aydınlanmak/düzeltmek","level":"B1"},{"english":"climb down","turkish":"vazgeçmek","level":"B2"},{"english":"close down","turkish":"kapatmak","level":"B2"},{"english":"come along","turkish":"gelmek/ilerlemek","level":"B1"},{"english":"come around","turkish":"fikrini değiştirmek","level":"B2"},{"english":"come down","turkish":"düşmek/azalmak","level":"B1"},{"english":"come forward","turkish":"gönüllü olmak","level":"B2"},{"english":"come through","turkish":"başarılı olmak","level":"B2"},{"english":"cool down","turkish":"sakinleşmek","level":"B1"},{"english":"cough up","turkish":"ödemek (isteksizce)","level":"B2"},{"english":"crack down","turkish":"sıkı kontrol uygulamak","level":"B2"},{"english":"creep in","turkish":"yavaşça girmek","level":"B2"},{"english":"cross out","turkish":"çizmek (silmek)","level":"B1"},{"english":"cut back","turkish":"azaltmak","level":"B1"},{"english":"cut in","turkish":"araya girmek","level":"B2"},{"english":"cut through","turkish":"kestirmeden gitmek","level":"B2"},{"english":"die away","turkish":"azalmak","level":"B2"},{"english":"die down","turkish":"sönmek/azalmak","level":"B2"},{"english":"die out","turkish":"yok olmak","level":"B2"},{"english":"dig up","turkish":"bulmak (toprakta)","level":"B2"},{"english":"dish out","turkish":"dağıtmak/azarlamak","level":"B2"},{"english":"do away","turkish":"ortadan kaldırmak","level":"B2"},{"english":"do up","turkish":"süslemek/tamir etmek","level":"B2"},{"english":"doze off","turkish":"uykuya dalmak","level":"B2"},{"english":"drag on","turkish":"uzamak","level":"B2"},{"english":"draw in","turkish":"kararmaya başlamak","level":"B2"},{"english":"draw out","turkish":"uzatmak","level":"B2"},{"english":"dream away","turkish":"hayallere dalmak","level":"B2"},{"english":"dream up","turkish":"uydurmak","level":"B2"},{"english":"drink up","turkish":"içip bitirmek","level":"B2"},{"english":"drive away","turkish":"kovmak","level":"B2"},{"english":"drive off","turkish":"uzaklaştırmak","level":"B2"},{"english":"drum up","turkish":"uyandırmak","level":"B2"},{"english":"dry out","turkish":"kurumak","level":"B2"},{"english":"dry up","turkish":"kurumak/susmak","level":"B2"},{"english":"ease off","turkish":"hafifleştirmek","level":"B2"},{"english":"eat up","turkish":"bitirmek","level":"A2"},{"english":"egg on","turkish":"kışkırtmak","level":"B2"},{"english":"face up to","turkish":"kabul etmek","level":"B2"},{"english":"fade away","turkish":"solmak","level":"B2"},{"english":"fade out","turkish":"solup gitmek","level":"B2"},{"english":"fan out","turkish":"yayılmak","level":"B2"},{"english":"farm out","turkish":"dışarı vermek","level":"B2"},{"english":"fast-talk","turkish":"kandırmak","level":"B2"},{"english":"fight off","turkish":"püskürtmek","level":"B2"},{"english":"file away","turkish":"dosyalamak","level":"B2"},{"english":"fill up","turkish":"doldurmak","level":"B1"},{"english":"filter out","turkish":"süzmek","level":"B2"},{"english":"find fault","turkish":"kusur bulmak","level":"B2"},{"english":"fish for","turkish":"dolaylı sormak","level":"B2"},{"english":"fit in","turkish":"uyum sağlamak","level":"B1"},{"english":"fix up","turkish":"ayarlamak","level":"B2"},{"english":"flare up","turkish":"alevlenmek","level":"B2"},{"english":"flesh out","turkish":"detaylandırmak","level":"B2"},{"english":"flounce out","turkish":"öfkeyle çıkmak","level":"B2"},{"english":"follow up","turkish":"takip etmek","level":"B2"},{"english":"fool around","turkish":"oyalanmak","level":"B2"},{"english":"forgo","turkish":"vazgeçmek","level":"B2"},{"english":"fizzle out","turkish":"sönmek","level":"B2"},{"english":"fly off","turkish":"hızla uçmak","level":"B2"},{"english":"fold up","turkish":"katlanmak","level":"B2"},{"english":"follow through","turkish":"tamamlamak","level":"B2"},{"english":"footle around","turkish":"vakit öldürmek","level":"B2"},{"english":"fork out/over","turkish":"ödemek (pahalı)","level":"B2"},{"english":"free up","turkish":"boşaltmak","level":"B2"},{"english":"freshen up","turkish":"tazelemek","level":"B1"},{"english":"frighten off","turkish":"korkutmak","level":"B2"},{"english":"front up","turkish":"ortaya çıkmak","level":"B2"},{"english":"fuddle up","turkish":"karıştırmak","level":"B2"},{"english":"fuel up","turkish":"yakıt doldurmak","level":"B2"},{"english":"gang up","turkish":"gruplaşmak","level":"B2"},{"english":"gas up","turkish":"yakıt almak","level":"B2"},{"english":"gear up","turkish":"hazırlanmak","level":"B2"},{"english":"get across","turkish":"anlatmak","level":"B1"},{"english":"get ahead","turkish":"ilerlemek","level":"B1"},{"english":"get around","turkish":"etrafından dolaşmak","level":"B1"},{"english":"get at","turkish":"ima etmek","level":"B2"},{"english":"get away with","turkish":"kurtulmak","level":"B1"},{"english":"get down","turkish":"üzülmek/indirmek","level":"B1"},{"english":"get in on","turkish":"dahil olmak","level":"B2"},{"english":"get round to","turkish":"vakit bulmak","level":"B2"},{"english":"get together","turkish":"toplanmak","level":"B1"},{"english":"give off","turkish":"yaymak (koku)","level":"B2"},{"english":"give oneself up","turkish":"teslim olmak","level":"B2"},{"english":"gloss over","turkish":"üzerinde durmamak","level":"B2"},{"english":"go after","turkish":"peşinden koşmak","level":"B2"},{"english":"go against","turkish":"karşı gelmek","level":"B2"},{"english":"go along with","turkish":"kabul etmek","level":"B1"},{"english":"go away","turkish":"gitmek","level":"A2"},{"english":"go by","turkish":"geçmek/adı olmak","level":"B2"},{"english":"go for","turkish":"tercih etmek/saldırmak","level":"B1"},{"english":"go into","turkish":"incelemek","level":"B1"},{"english":"go off","turkish":"patlamak/çalmak","level":"B1"},{"english":"go through","turkish":"yaşamak/incelemek","level":"B1"},{"english":"go under","turkish":"batmak","level":"B2"},{"english":"go with","turkish":"uymak/gitmek","level":"B1"},{"english":"gross out","turkish":"iğrendirmek","level":"B2"},{"english":"grow apart","turkish":"uzaklaşmak","level":"B2"},{"english":"grow into","turkish":"büyüyüp uymak","level":"B2"},{"english":"hand down","turkish":"miras bırakmak","level":"B2"},{"english":"hand in","turkish":"teslim etmek","level":"B1"},{"english":"hand out","turkish":"dağıtmak","level":"B1"},{"english":"hand over","turkish":"teslim etmek","level":"B1"},{"english":"hang around","turkish":"oyalanmak","level":"B1"},{"english":"hang back","turkish":"geri kalmak","level":"B2"},{"english":"hash out","turkish":"tartışmak","level":"B2"},{"english":"have on","turkish":"giymiş olmak","level":"B1"},{"english":"head off","turkish":"engellemek","level":"B2"},{"english":"head over heels","turkish":"âşık olmak","level":"B2"},{"english":"hit it off","turkish":"anlaşmak","level":"B2"},{"english":"hit on","turkish":"bulmak/flört etmek","level":"B2"},{"english":"hold down","turkish":"bastırmak/sürdürmek","level":"B2"},{"english":"hold out","turkish":"direnmek","level":"B2"},{"english":"hole up","turkish":"saklanmak","level":"B2"},{"english":"home in","turkish":"odaklanmak","level":"B2"},{"english":"hook up","turkish":"bağlanmak/buluşmak","level":"B2"},{"english":"hunker down","turkish":"yerleşmek","level":"B2"},{"english":"hunt down","turkish":"bulup çıkarmak","level":"B2"},{"english":"iron out","turkish":"çözmek","level":"B2"},{"english":"jack up","turkish":"artırmak","level":"B2"},{"english":"jazz up","turkish":"renklendirmek","level":"B2"},{"english":"jump in","turkish":"başlamak","level":"B2"},{"english":"keep around","turkish":"saklamak","level":"B2"},{"english":"keep away","turkish":"uzak durmak","level":"B2"},{"english":"keep down","turkish":"bastırmak","level":"B2"},{"english":"key in","turkish":"yazmak (bilgisayar)","level":"B2"},{"english":"kick around","turkish":"tartışmak","level":"B2"},{"english":"kick back","turkish":"rahatlamak","level":"B2"},{"english":"kick in","turkish":"başlamak/katkı sağlamak","level":"B2"},{"english":"kick out","turkish":"kovmak","level":"B2"},{"english":"kiss off","turkish":"umursamamak","level":"B2"},{"english":"knock about","turkish":"gezmek","level":"B2"},{"english":"knock back","turkish":"içmek","level":"B2"},{"english":"knock down","turkish":"yıkmak/indirmek","level":"B2"},{"english":"knock off","turkish":"bitirmek/sahteleştirmek","level":"B2"},{"english":"knock over","turkish":"devirmek","level":"B2"},{"english":"knuckle down","turkish":"ciddiye almak","level":"B2"},{"english":"lap up","turkish":"hevesle kabul etmek","level":"B2"},{"english":"lash out","turkish":"saldırmak","level":"B2"},{"english":"lay off","turkish":"işten çıkarmak","level":"B1"},{"english":"lead on","turkish":"kandırmak","level":"B2"},{"english":"leak out","turkish":"sızmak","level":"B2"},{"english":"leap at","turkish":"hemen kabul etmek","level":"B2"},{"english":"level off","turkish":"sabitlenmek","level":"B2"},{"english":"lie around","turkish":"yayılmak","level":"B2"},{"english":"light up","turkish":"yanmak/aydınlanmak","level":"B2"},{"english":"line up","turkish":"kuyruğa girmek/düzenlemek","level":"B1"},{"english":"live down","turkish":"unutturmak","level":"B2"},{"english":"live it up","turkish":"eğlenmek","level":"B2"},{"english":"load up","turkish":"doldurmak","level":"B2"},{"english":"lock in","turkish":"garantiye almak","level":"B2"}]